LICENSE.txt
README.md
pyproject.toml
src/electrography/__init__.py
src/electrography/boards.py
src/electrography/data.py
src/electrography.egg-info/PKG-INFO
src/electrography.egg-info/SOURCES.txt
src/electrography.egg-info/dependency_links.txt
src/electrography.egg-info/requires.txt
src/electrography.egg-info/top_level.txt
src/zippy_cython_functions/data_helper_functions.pyx