Metadata-Version: 2.4
Name: electrography
Version: 1.1.0
Summary: Python package to record and analyse data from OpenBCI boards
Author-email: Edwin Dalmaijer <edwin@dalmaijer.org>
License:                     GNU GENERAL PUBLIC LICENSE
Project-URL: Homepage, https://www.dalmaijer.org
Project-URL: Bug Reports, https://github.com/esdalmaijer/electrography/issues
Project-URL: Source, https://github.com/esdalmaijer/electrography
Keywords: electrophysiology,electrocardiography,electrogastrography,electroencephalography
Classifier: Development Status :: 5 - Production/Stable
Classifier: Intended Audience :: Science/Research
Classifier: Topic :: Scientific/Engineering
Classifier: Programming Language :: Python :: 3
Classifier: License :: OSI Approved :: Apache Software License
Requires-Python: >=3.9
License-File: LICENSE.txt
Requires-Dist: brainflow
Requires-Dist: numpy
Requires-Dist: scipy
Requires-Dist: scikit-learn
Dynamic: license-file
